luckydonaldUtils/__init__.py
luckydonaldUtils/clazzes.py
luckydonaldUtils/clazzes.pyi
luckydonaldUtils/compat.py
luckydonaldUtils/decorators.py
luckydonaldUtils/download.py
luckydonaldUtils/encoding.py
luckydonaldUtils/exceptions.py
luckydonaldUtils/functions.py
luckydonaldUtils/holder.py
luckydonaldUtils/interactions.py
luckydonaldUtils/iterators.py
luckydonaldUtils/json.py
luckydonaldUtils/selfupdate.py
luckydonaldUtils/store.py
luckydonaldUtils/text.py
luckydonaldUtils/xml.py
luckydonaldUtils/dependencies/__init__.py
luckydonaldUtils/dependencies/install.py
luckydonaldUtils/dependencies/pip_interface.py
luckydonaldUtils/dependencies/pip_interface_fallback.py
luckydonaldUtils/dependencies/pip_interface_fallback_fallback.py
luckydonaldUtils/djangos/__init__.py
luckydonaldUtils/djangos/headers.py
luckydonaldUtils/djangos/requests.py
luckydonaldUtils/djangos/responses.py
luckydonaldUtils/djangos/middleware/__init__.py
luckydonaldUtils/djangos/middleware/access.py
luckydonaldUtils/djangos/middleware/headers.py
luckydonaldUtils/eastereggs/__init__.py
luckydonaldUtils/eastereggs/headers.py
luckydonaldUtils/eastereggs/ponies.py
luckydonaldUtils/eastereggs/quotes.py
luckydonaldUtils/files/__init__.py
luckydonaldUtils/files/basics.py
luckydonaldUtils/files/hierarchies.py
luckydonaldUtils/files/mime.py
luckydonaldUtils/files/name.py
luckydonaldUtils/files/temp.py
luckydonaldUtils/files/tree.py
luckydonaldUtils/flasks/__init__.py
luckydonaldUtils/flasks/launcher.py
luckydonaldUtils/flasks/routing.py
luckydonaldUtils/images/__init__.py
luckydonaldUtils/images/color.py
luckydonaldUtils/imports/__init__.py
luckydonaldUtils/imports/relative.py
luckydonaldUtils/imports/representation.py
luckydonaldUtils/logger/__init__.py
luckydonaldUtils/logger/py3.py
luckydonaldUtils/network/__init__.py
luckydonaldUtils/network/ip.py
luckydonaldUtils/network/mod_wsgi/__init__.py
luckydonaldUtils/network/mod_wsgi/reloader.py
luckydonaldUtils/regex/__init__.py
luckydonaldUtils/regex/github.py
luckydonald_utils-0.84.dist-info/LICENSE
luckydonald_utils-0.84.dist-info/METADATA
luckydonald_utils-0.84.dist-info/WHEEL
luckydonald_utils-0.84.dist-info/top_level.txt
luckydonald_utils-0.84.dist-info/RECORD
