Metadata-Version: 2.1
Name: luckydonald-utils
Version: 0.84
Summary: A collection of utilities I use across different projects
Home-page: https://github.com/luckydonald/luckydonald-utils
Author: luckydonald
Author-email: code_utils@luckydonald.de
License: GPLv2+
Keywords: luckydonald utils utilities utility python dependencies dependency download progress bar encoding files interactions json update store text xml time network logger color images webserver django CSRF headers eastereggs decorator holder assert raise is None ponies pony
Classifier: Development Status :: 4 - Beta
Classifier: Intended Audience :: Developers
Classifier: Topic :: Utilities
Classifier: License :: OSI Approved :: GNU General Public License v3 or later (GPLv3+)
License-File: LICENSE
Requires-Dist: pip
Requires-Dist: setuptools
Requires-Dist: DictObject
